flow_tools
