Metadata-Version: 1.1
Name: flow-tools
Version: 1.0.1
Summary: Integrations and scripts for jira and gerrit
Home-page: https://github.com/cheshirekow/flow_tools
Author: Josh Bialkowski
Author-email: josh.bialkowski@gmail.com
License: UNKNOWN
Download-URL: https://github.com/cheshirekow/flow_tools/archive/1.0.1.tar.gz
Keywords: jira,gerrit
Platform: UNKNOWN
